sim_sci_test_monorepo/__init__.py
sim_sci_test_monorepo/core/__init__.py
sim_sci_test_monorepo/core/_version.py
sim_sci_test_monorepo/core/utils.py
sim_sci_test_monorepo_core-0.0.13.dist-info/METADATA
sim_sci_test_monorepo_core-0.0.13.dist-info/WHEEL
sim_sci_test_monorepo_core-0.0.13.dist-info/top_level.txt
sim_sci_test_monorepo_core-0.0.13.dist-info/RECORD
